MANIFEST.in
README.rst
setup.py
omsa_alert.egg-info/PKG-INFO
omsa_alert.egg-info/SOURCES.txt
omsa_alert.egg-info/dependency_links.txt
omsa_alert.egg-info/not-zip-safe
omsa_alert.egg-info/requires.txt
omsa_alert.egg-info/top_level.txt
omsaalert/__init__.py
omsaalert/notify.py
omsaalert/parser.py
omsaalert/pdisk_parser.py
omsaalert/utility.py
omsaalert/vdisk_parser.py
omsaalert/config/__init__.py
omsaalert/config/email.py
omsaalert/resources/README.rst
omsaalert/resources/requirements.txt
omsaalert/resources/version.txt
omsaalert/resources/scripts/oa_check