Metadata-Version: 1.0
Name: omsa-alert
Version: 0.2.0
Summary: Scan OMSA's omreport tool's output for issues
Home-page: https://github.com/dsoprea/omsa_alert
Author: Dustin Oprea
Author-email: myselfasunder@gmail.com
License: GPL 2
Keywords: omsa omreport
Platform: UNKNOWN
